README.md
license.txt
setup.py
only_test_pack/__init__.py
only_test_pack/teste1.py
only_test_pack/teste2.py
pacote_teste_3_victor_2024.egg-info/PKG-INFO
pacote_teste_3_victor_2024.egg-info/SOURCES.txt
pacote_teste_3_victor_2024.egg-info/dependency_links.txt
pacote_teste_3_victor_2024.egg-info/top_level.txt